dumbtils/__init__.py
dumbtils/_c1.py
dumbtils/_c2.py
dumbtils/bingonacci.py
dumbtils/common.py
dumbtils/procmax.py
dumbtils/tictoc.py
dumbtils/timeprog.py
dumbtils/ucp.py
dumbtils-0.2.1.dist-info/LICENSE
dumbtils-0.2.1.dist-info/METADATA
dumbtils-0.2.1.dist-info/WHEEL
dumbtils-0.2.1.dist-info/entry_points.txt
dumbtils-0.2.1.dist-info/top_level.txt
dumbtils-0.2.1.dist-info/zip-safe
dumbtils-0.2.1.dist-info/RECORD
