Metadata-Version: 2.1
Name: dumbtils
Version: 0.2.1
Summary: Dumb Utilities.
Home-page: https://github.com/paaksing/dumbtils
Author: Paaksing
Author-email: paaksingtech@gmail.com
License: MIT
Keywords: utils
Platform: UNKNOWN
Classifier: License :: OSI Approved :: MIT License
Classifier: Natural Language :: English
License-File: LICENSE
